saspy/SASLogLexer.py
saspy/__init__.py
saspy/autocfg.py
saspy/libname_gen.sas
saspy/sasViyaML.py
saspy/sas_magic.py
saspy/sasbase.py
saspy/sascfg.py
saspy/sasdata.py
saspy/sasdecorator.py
saspy/sasets.py
saspy/sasexceptions.py
saspy/sasiocom.py
saspy/sasiohttp.py
saspy/sasioiom.py
saspy/sasiostdio.py
saspy/sasml.py
saspy/sasproccommons.py
saspy/sasqc.py
saspy/sasresults.py
saspy/sasstat.py
saspy/sastabulate.py
saspy/sasutil.py
saspy/version.py
saspy/java/saspyiom.jar
saspy/java/iomclient/log4j-1.2-api-2.12.4.jar
saspy/java/iomclient/log4j-1.2-api-2.17.1.jar
saspy/java/iomclient/log4j-api-2.12.4.jar
saspy/java/iomclient/log4j-api-2.17.1.jar
saspy/java/iomclient/log4j-core-2.12.4.jar
saspy/java/iomclient/log4j-core-2.17.1.jar
saspy/java/iomclient/sas.core.jar
saspy/java/iomclient/sas.security.sspi.jar
saspy/java/iomclient/sas.svc.connection.jar
saspy/java/pyiom/cancel.class
saspy/java/pyiom/cancel.java
saspy/java/pyiom/saspy2j.class
saspy/java/pyiom/saspy2j.java
saspy/java/thirdparty/NOTICE.md
saspy/java/thirdparty/glassfish-corba-internal-api.jar
saspy/java/thirdparty/glassfish-corba-omgapi.jar
saspy/java/thirdparty/glassfish-corba-orb.jar
saspy/java/thirdparty/pfl-basic.jar
saspy/java/thirdparty/pfl-tf.jar
saspy/scripts/run_sas.py
saspy-5.103.2.dist-info/licenses/LICENSE.md
saspy-5.103.2.dist-info/METADATA
saspy-5.103.2.dist-info/WHEEL
saspy-5.103.2.dist-info/top_level.txt
saspy-5.103.2.dist-info/RECORD
