Metadata-Version: 2.4
Name: saspy
Version: 5.103.2
Summary: A Python interface to SAS
Home-page: https://github.com/sassoftware/saspy
Author: Tom Weber
Author-email: Tom.Weber@sas.com
Classifier: Programming Language :: Python :: 3
Classifier: Programming Language :: Python :: 3.4
Classifier: Programming Language :: Python :: 3.5
Classifier: Topic :: System :: Shells
Classifier: License :: OSI Approved :: Apache Software License
License-File: LICENSE.md
Provides-Extra: iomcom
Requires-Dist: pypiwin32; extra == "iomcom"
Provides-Extra: colorlog
Requires-Dist: pygments; extra == "colorlog"
Provides-Extra: parquet
Requires-Dist: pyarrow; extra == "parquet"
Provides-Extra: pandas
Requires-Dist: pandas; extra == "pandas"
Dynamic: author
Dynamic: author-email
Dynamic: classifier
Dynamic: description
Dynamic: home-page
Dynamic: license-file
Dynamic: provides-extra
Dynamic: summary
